peak_finder/__init__.py
peak_finder/anomaly.py
peak_finder/anomaly_group.py
peak_finder/application.py
peak_finder/constants.py
peak_finder/dash_application.py
peak_finder/driver.py
peak_finder/images/peak_finder_app.png
peak_finder/layout.py
peak_finder/line_anomaly.py
peak_finder/line_data.py
peak_finder/line_group.py
peak_finder/line_position.py
peak_finder/params.py
peak_finder/utils.py
peak_finder-assets/FlinFlon_tem_aoi.geoh5
peak_finder-assets/__init__.py
peak_finder-assets/uijson/peak_finder.ui.json
peak_finder-assets/uijson/test.geoh5
peak_finder_app-0.2.1.dist-info/LICENSE
peak_finder_app-0.2.1.dist-info/METADATA
peak_finder_app-0.2.1.dist-info/WHEEL
peak_finder_app-0.2.1.dist-info/RECORD
