Metadata-Version: 2.3
Name: peak-finder-app
Version: 0.2.1
Summary: Peak Finder App
License: MIT
Author: Mira Geoscience
Author-email: support@mirageoscience.com
Maintainer: Dominique Fournier
Maintainer-email: dominiquef@mirageoscience.com
Requires-Python: >=3.10,<3.13
Classifier: Development Status :: 3 - Alpha
Classifier: Intended Audience :: Science/Research
Classifier: License :: OSI Approved :: MIT License
Classifier: Natural Language :: English
Classifier: Operating System :: Microsoft :: Windows
Classifier: Operating System :: POSIX
Classifier: Operating System :: Unix
Classifier: Programming Language :: Python
Classifier: Programming Language :: Python :: 3
Classifier: Programming Language :: Python :: 3.10
Classifier: Programming Language :: Python :: 3.11
Classifier: Programming Language :: Python :: 3.12
Classifier: Topic :: Scientific/Engineering
Classifier: Topic :: Scientific/Engineering :: Mathematics
Classifier: Topic :: Scientific/Engineering :: Physics
Provides-Extra: dash
Requires-Dist: curve-apps (>=0.2.1,<0.3.dev)
Requires-Dist: dash (>=2.12,<3.0) ; extra == "dash"
Requires-Dist: dash-core-components (>=2,<3.dev) ; extra == "dash"
Requires-Dist: dash-daq (==0.5.*) ; extra == "dash"
Requires-Dist: dash-html-components (>=2,<3.dev) ; extra == "dash"
Requires-Dist: dash-table (>=5,<6.dev) ; extra == "dash"
Requires-Dist: dask (>=2025.3,<2025.4.dev)
Requires-Dist: distributed (>=2025.3,<2025.4.dev)
Requires-Dist: flask (>=3.0.3,<4.0.0) ; extra == "dash"
Requires-Dist: geoapps-utils (>=0.5.0,<0.6.dev)
Requires-Dist: geoh5py (>=0.11.0,<0.12.dev)
Requires-Dist: numpy (>=1.26.0,<1.27.0)
Requires-Dist: plotly (>=5.19.0,<5.20.0)
Requires-Dist: pyqtwebengine (>=5.15.2,<5.16.dev) ; (python_version < "3.11") and (extra == "dash")
Requires-Dist: pyside2 (>=5.15.2,<5.16.dev) ; (python_version < "3.11") and (extra == "dash")
Requires-Dist: scipy (>=1.14.0,<1.15.0)
Requires-Dist: tqdm (>=4.66.1,<5.0.0)
Project-URL: Documentation, https://mirageoscience-peak-finder-app.readthedocs-hosted.com/
Project-URL: Homepage, https://www.mirageoscience.com/mining-industry-software/python-integration/
Project-URL: Repository, https://github.com/MiraGeoscience/peak-finder-app
